configurables/__init__.py
configurables/base.py
configurables/defres.py
configurables/exception.py
configurables/identifier.py
configurables/loader.py
configurables/misc.py
configurables/option.py
configurables/options.py
configurables/parent.py
configurables/parse.py
configurables/util.py
configurables/sphinx/__init__.py
configurables/sphinx/doc.py
configurables/test/__init__.py
configurables/test/conftest.py
configurables/test/test_configurable.py
configurables-1.2.2.dist-info/METADATA
configurables-1.2.2.dist-info/WHEEL
configurables-1.2.2.dist-info/licenses/LICENSE
configurables-1.2.2.dist-info/RECORD
