Metadata-Version: 2.4
Name: configurables
Version: 1.2.2
Summary: A python library for providing complex validation for object attributes, and for dynamically loading objects from config files.
Project-URL: Homepage, https://github.com/Digichem-Project/configurables
Project-URL: Issues, https://github.com/Digichem-Project/configurables/issues
Author-email: "Oliver S. Lee" <osl@digi-chem.ac.uk>
License: Copyright 2024 Oliver S. Lee
License-File: LICENSE
Classifier: License :: OSI Approved :: BSD License
Classifier: Operating System :: Unix
Classifier: Programming Language :: Python :: 3
Requires-Python: >=3.8
Requires-Dist: deepmerge
Requires-Dist: pyyaml
Provides-Extra: test
Requires-Dist: pytest; extra == 'test'
